autopilot/__init__.py
autopilot/agents/__init__.py
autopilot/agents/base.py
autopilot/agents/pilot.py
autopilot/agents/terminal.py
autopilot/data/__init__.py
autopilot/data/interfaces/__init__.py
autopilot/data/interfaces/base.py
autopilot/data/interfaces/datajoint.py
autopilot/data/interfaces/nwb.py
autopilot/data/interfaces/tables.py
autopilot/data/modeling/__init__.py
autopilot/data/modeling/base.py
autopilot/data/modeling/links.py
autopilot/data/models/__init__.py
autopilot/data/models/biography.py
autopilot/data/models/protocol.py
autopilot/data/models/researcher.py
autopilot/data/models/subject.py
autopilot/data/subject.py
autopilot/data/units/__init__.py
autopilot/data/units/base.py
autopilot/data/units/derived.py
autopilot/exceptions.py
autopilot/external/__init__.py
autopilot/gui/__init__.py
autopilot/gui/dialog.py
autopilot/gui/gui.py
autopilot/gui/menus/__init__.py
autopilot/gui/menus/file.py
autopilot/gui/menus/plots.py
autopilot/gui/menus/plugins.py
autopilot/gui/menus/swarm.py
autopilot/gui/menus/tests.py
autopilot/gui/menus/tools.py
autopilot/gui/plots/__init__.py
autopilot/gui/plots/geom.py
autopilot/gui/plots/info.py
autopilot/gui/plots/plot.py
autopilot/gui/plots/video.py
autopilot/gui/styles.py
autopilot/gui/widgets/__init__.py
autopilot/gui/widgets/input.py
autopilot/gui/widgets/list.py
autopilot/gui/widgets/model.py
autopilot/gui/widgets/protocol.py
autopilot/gui/widgets/subject.py
autopilot/gui/widgets/terminal.py
autopilot/hardware/__init__.py
autopilot/hardware/cameras.py
autopilot/hardware/gpio.py
autopilot/hardware/i2c.py
autopilot/hardware/usb.py
autopilot/networking/__init__.py
autopilot/networking/message.py
autopilot/networking/node.py
autopilot/networking/station.py
autopilot/prefs.py
autopilot/root.py
autopilot/setup/__init__.py
autopilot/setup/__main__.py
autopilot/setup/forms.py
autopilot/setup/install_pyspin.sh
autopilot/setup/request_helpers.py
autopilot/setup/run_script.py
autopilot/setup/scripts.py
auto_pi_lot-0.5.1.dist-info/LICENSE
auto_pi_lot-0.5.1.dist-info/METADATA
auto_pi_lot-0.5.1.dist-info/WHEEL
auto_pi_lot-0.5.1.dist-info/RECORD
