Metadata-Version: 2.1
Name: auto-pi-lot
Version: 0.5.1
Summary: Distributed behavioral experiments
Home-page: https://docs.auto-pi-lot.com
License: MPL-2.0
Author: Jonny Saunders
Author-email: j@nny.fyi
Requires-Python: >=3.9,<3.13
Classifier: Development Status :: 4 - Beta
Classifier: Intended Audience :: Developers
Classifier: Intended Audience :: Education
Classifier: Intended Audience :: End Users/Desktop
Classifier: Intended Audience :: Science/Research
Classifier: License :: OSI Approved
Classifier: License :: OSI Approved :: Mozilla Public License 2.0 (MPL 2.0)
Classifier: Natural Language :: English
Classifier: Operating System :: MacOS
Classifier: Operating System :: POSIX :: Linux
Classifier: Programming Language :: Python :: 3
Classifier: Programming Language :: Python :: 3.9
Classifier: Programming Language :: Python :: 3.10
Classifier: Programming Language :: Python :: 3.11
Classifier: Programming Language :: Python :: 3.12
Classifier: Programming Language :: Python :: 3.8
Classifier: Topic :: Scientific/Engineering
Provides-Extra: docs
Provides-Extra: extra-interfaces
Provides-Extra: pilot
Provides-Extra: plotting
Provides-Extra: terminal
Provides-Extra: tests
Requires-Dist: JACK-Client (>=0.5.3,<0.6.0) ; extra == "pilot"
Requires-Dist: PySide6 (>=6.6.1) ; extra == "terminal" or extra == "docs" or extra == "tests"
Requires-Dist: Sphinx (>=6.0.0,<7.0.0) ; extra == "docs"
Requires-Dist: altair (>=4.1.0,<5.0.0) ; extra == "docs" or extra == "plotting"
Requires-Dist: autodoc_pydantic (>=1.7.0,<2.0.0) ; extra == "docs"
Requires-Dist: autodocsumm (>=0.2.7,<0.3.0) ; extra == "docs"
Requires-Dist: blosc2 (>=2.4.0)
Requires-Dist: bokeh (>=2.4.2,<3.0.0) ; extra == "docs" or extra == "plotting"
Requires-Dist: cffi (>=1.15.0,<2.0.0)
Requires-Dist: colorcet (>=3.0.0,<4.0.0) ; extra == "docs" or extra == "plotting"
Requires-Dist: coveralls (>=3.3.1,<4.0.0) ; extra == "tests"
Requires-Dist: inputs (>=0.5,<0.6)
Requires-Dist: matplotlib (>=3.5.1,<4.0.0) ; extra == "docs"
Requires-Dist: myst_parser (>=3.0.0,<4.0.0) ; extra == "docs"
Requires-Dist: npyscreen (>=4.10.5,<5.0.0)
Requires-Dist: numpy (>=1.20.0,<2.0.0)
Requires-Dist: pandas (>=1.4.0)
Requires-Dist: parse (>=1.19.0,<2.0.0)
Requires-Dist: pigpio-autopilot (>=1.79,<2.0)
Requires-Dist: pydantic (>=1.9.0,<2.0.0)
Requires-Dist: pylint (>=2.12.2,<3.0.0) ; extra == "tests"
Requires-Dist: pynwb (>=2.0.0,<3.0.0,!=2.5.1) ; extra == "docs" or extra == "extra-interfaces"
Requires-Dist: pyqtgraph (>=0.13.3,<0.14.0) ; extra == "terminal" or extra == "docs" or extra == "tests"
Requires-Dist: pytest (>=7.0.0,<8.0.0) ; extra == "docs" or extra == "tests"
Requires-Dist: pytest-cov (>=3.0.0,<4.0.0) ; extra == "tests"
Requires-Dist: pytest-mock (>=3.14.0,<4.0.0) ; extra == "tests"
Requires-Dist: pytest-qt (>=4.3.0) ; extra == "tests"
Requires-Dist: pyzmq (>=25.0.0)
Requires-Dist: requests (>=2.26.0)
Requires-Dist: rich (>=11.2.0,<12.0.0) ; extra == "docs" or extra == "tests"
Requires-Dist: scikit-learn (>=1.0.1,<2.0.0) ; extra == "docs"
Requires-Dist: scikit-video (>=1.1.11)
Requires-Dist: scipy (>=1.7.0)
Requires-Dist: sphinx-rtd-theme (>=1.0.0,<2.0.0) ; extra == "docs"
Requires-Dist: sphinxcontrib-bibtex (>=2.4.1,<3.0.0) ; extra == "docs"
Requires-Dist: tables (>=3.9.0)
Requires-Dist: tornado (>=6.1.0,<7.0.0)
Requires-Dist: tqdm (>=4.62.3)
Requires-Dist: validators (>=0.18.2,<0.19.0)
Project-URL: Repository, https://github.com/auto-pi-lot/autopilot
